approx/__init__.py
approx/equals.py
approx-0.0.1.dist-info/License
approx-0.0.1.dist-info/METADATA
approx-0.0.1.dist-info/WHEEL
approx-0.0.1.dist-info/top_level.txt
approx-0.0.1.dist-info/RECORD
