Metadata-Version: 2.1
Name: approx
Version: 0.0.1
Summary: Set of tools for comparing complex objects
Home-page: https://github.com/ivanovmg/approx
Author: Maxim Ivanov
Author-email: ivanovmg@gmail.com
Maintainer: Maxim Ivanov
Maintainer-email: ivanovmg@gmail.com
License: BSD license
Keywords: approx
Platform: UNKNOWN
Classifier: Development Status :: 3 - Alpha
Classifier: Intended Audience :: Developers
Classifier: Programming Language :: Python :: 3.6
